Metadata-Version: 1.0
Name: pr-distr-set
Version: 0.1
Summary: Gaussian and Binomial distributions
Home-page: UNKNOWN
Author: Sushant
Author-email: UNKNOWN
License: UNKNOWN
Platform: UNKNOWN
